cnlpt/BaselineModels.py
cnlpt/CnlpModelForClassification.py
cnlpt/HierarchicalTransformer.py
cnlpt/__init__.py
cnlpt/__main__.py
cnlpt/cnlp_args.py
cnlpt/cnlp_data.py
cnlpt/cnlp_metrics.py
cnlpt/cnlp_predict.py
cnlpt/cnlp_processors.py
cnlpt/dapt.py
cnlpt/select_hyperparameters.py
cnlpt/thyme_eval.py
cnlpt/train_system.py
cnlpt/_cli/main.py
cnlpt/_cli/rest.py
cnlpt/api/__init__.py
cnlpt/api/cnn_rest.py
cnlpt/api/current_rest.py
cnlpt/api/dtr_rest.py
cnlpt/api/event_rest.py
cnlpt/api/hier_rest.py
cnlpt/api/negation_rest.py
cnlpt/api/temporal_rest.py
cnlpt/api/termexists_rest.py
cnlpt/api/timex_rest.py
cnlpt/api/utils.py
cnlpt/data/__init__.py
cnlpt/data/preprocess_i2b2_2008.py
cnlpt/data/transform_prot.py
cnlpt/data/transform_uci_drug.py
cnlpt/notebooks/viz_negation.ipynb
cnlpt/notebooks/viz_params.ipynb
cnlpt/tests/test_multiple_systems.sh
cnlp_transformers-0.7.1.dist-info/LICENSE
cnlp_transformers-0.7.1.dist-info/METADATA
cnlp_transformers-0.7.1.dist-info/WHEEL
cnlp_transformers-0.7.1.dist-info/entry_points.txt
cnlp_transformers-0.7.1.dist-info/top_level.txt
cnlp_transformers-0.7.1.dist-info/RECORD
