Metadata-Version: 2.1
Name: cnlp-transformers
Version: 0.7.1
Summary: Transformers for Clinical NLP
Author-email: "Machine Learning for Medical Language Lab @ CHIP" <Timothy.Miller@childrens.harvard.edu>
Project-URL: Homepage, https://github.com/Machine-Learning-for-Medical-Language/cnlp_transformers/
Project-URL: Bug Tracker, https://github.com/Machine-Learning-for-Medical-Language/cnlp_transformers/issues
Classifier: Programming Language :: Python :: 3.9
Classifier: Programming Language :: Python :: 3.10
Classifier: Programming Language :: Python :: 3.11
Classifier: Operating System :: OS Independent
Classifier: License :: OSI Approved :: Apache Software License
Requires-Python: <3.12,>=3.9
License-File: LICENSE
Requires-Dist: anaforatools~=1.1.0
Requires-Dist: click>=8.1.7
Requires-Dist: datasets~=2.21.0
Requires-Dist: fastapi~=0.115.2
Requires-Dist: httpx>=0.27.2
Requires-Dist: huggingface-hub>=0.9.0
Requires-Dist: nltk~=3.5
Requires-Dist: numpy~=2.0.2
Requires-Dist: pandas~=2.2.3
Requires-Dist: pydantic~=1.10.8
Requires-Dist: requests~=2.32.2
Requires-Dist: scikit-learn~=1.5.2
Requires-Dist: seqeval~=1.2.2
Requires-Dist: torch
Requires-Dist: transformers[torch]~=4.45
Requires-Dist: uvicorn[standard]~=0.32.0
